Workbook

Sheet Cover
B11: Discounted Cash Flow Model
B13: Table of Contents:
C15: Outputs
C17: Inputs
C19: Model
C24: Disclaimer:
C25: The following workbook and each cell in it has been protected using a password. It has been done so to preserve the formatting, formulas
C26: and ultimately the dynamicity of the model.
C27: If need be, suggestions and reviews can be made via E-Mail and/or Linkedin.
C28: Thank You, Have a Nice Day

Sheet Outputs
B8: Dashboard
B10: All Figures in INR Crores unless stated
C13: Main Outputs | K13: Main Inputs Taken
D15: Enterprise | E15: Equity | F15: Equity | K15: Terminal Multiple | O15: =Inputs!E94 -> 20
D16: Value | E16: Value | F16: Per Share | K16: WACC | O16: =Inputs!N88 -> 0.11590847
F17: INR/Share | K17: Net Debt | O17: =Inputs!E95 -> -3649.39
C18: Best Case | D18: =Inputs!G109 -> 572330.78 | E18: =D18-$O$17 -> 575980.17 | F18: =E18 / O18 -> 459.71759 | K18: Shares Outstanding | O18: =Inputs!E97 -> 1252.9
C19: Base Case | D19: =Inputs!G110 -> 515036.09 | E19: =D19-$O$17 -> 518685.48 | F19: =E19 / $O$18 -> 413.98794 | K19: Current Stock Price | O19: =Inputs!E98 -> 404.5
C20: Worst Case | D20: =Inputs!G111 -> 464836.83 | E20: =D20-$O$17 -> 468486.22 | F20: =E20 / $O$18 -> 373.92148
C24: Enterprise Value | K24: Equity Value
E26: Terminal Multiple | M26: Terminal Multiple
D28: =E28-1 -> 18 | E28: =F28-1 -> 19 | F28: =Inputs!E94 -> 20 | G28: =F28+1 -> 21 | H28: =G28+1 -> 22 | L28: =M28-1 -> 18 | M28: =N28-1 -> 19 | N28: =O15 -> 20 | O28: =N28+1 -> 21 | P28: =O28+1 -> 22
B29: WACC | C29: =C30-0.01 -> 0.095908474 | D29: =Model!E178 -> 505067.74 | E29: =Model!F178 -> 529470.15 | F29: =Model!G178 -> 553872.56 | G29: =Model!H178 -> 578274.97 | H29: =Model!I178 -> 602677.39 | J29: WACC | K29: =K30-0.01 -> 0.095908474 | L29: =D29-$O$17 -> 508717.13 | M29: =E29-$O$17 -> 533119.54 | N29: =F29-$O$17 -> 557521.95 | O29: =G29-$O$17 -> 581924.36 | P29: =H29-$O$17 -> 606326.78
C30: =C31-0.01 -> 0.10590847 | D30: =Model!E179 -> 487045.72 | E30: =Model!F179 -> 510523.45 | F30: =Model!G179 -> 534001.18 | G30: =Model!H179 -> 557478.91 | H30: =Model!I179 -> 580956.64 | K30: =K31-0.01 -> 0.10590847 | L30: =D30-$O$17 -> 490695.11 | M30: =E30-$O$17 -> 514172.84 | N30: =F30-$O$17 -> 537650.57 | O30: =G30-$O$17 -> 561128.3 | P30: =H30-$O$17 -> 584606.03
C31: =Inputs!N88 -> 0.11590847 | D31: =Model!E180 -> 469844.21 | E31: =Model!F180 -> 492440.15 | F31: =Model!G180 -> 515036.09 | G31: =Model!H180 -> 537632.04 | H31: =Model!I180 -> 560227.98 | K31: =O16 -> 0.11590847 | L31: =D31-$O$17 -> 473493.6 | M31: =E31-$O$17 -> 496089.54 | N31: =F31-$O$17 -> 518685.48 | O31: =G31-$O$17 -> 541281.43 | P31: =H31-$O$17 -> 563877.37
C32: =C31 + 0.01 -> 0.12590847 | D32: =Model!E181 -> 453418.73 | E32: =Model!F181 -> 475173.43 | F32: =Model!G181 -> 496928.14 | G32: =Model!H181 -> 518682.84 | H32: =Model!I181 -> 540437.55 | K32: =K31 + 0.01 -> 0.12590847 | L32: =D32-$O$17 -> 457068.12 | M32: =E32-$O$17 -> 478822.82 | N32: =F32-$O$17 -> 500577.53 | O32: =G32-$O$17 -> 522332.23 | P32: =H32-$O$17 -> 544086.94
C33: =C32 + 0.01 -> 0.13590847 | D33: =Model!E182 -> 437727.59 | E33: =Model!F182 -> 458679.4 | F33: =Model!G182 -> 479631.21 | G33: =Model!H182 -> 500583.03 | H33: =Model!I182 -> 521534.84 | K33: =K32 + 0.01 -> 0.13590847 | L33: =D33-$O$17 -> 441376.98 | M33: =E33-$O$17 -> 462328.79 | N33: =F33-$O$17 -> 483280.6 | O33: =G33-$O$17 -> 504232.42 | P33: =H33-$O$17 -> 525184.23
C38: Equity Value | K38: Premium (Discount) to Stock Price
E40: Terminal Multiple | M40: Terminal Multiple
D42: =E42-1 -> 18 | E42: =F42-1 -> 19 | F42: =O15 -> 20 | G42: =F42+1 -> 21 | H42: =G42+1 -> 22 | L42: =M42-1 -> 18 | M42: =N42-1 -> 19 | N42: =O15 -> 20 | O42: =N42+1 -> 21 | P42: =O42+1 -> 22
B43: WACC | C43: =C44-0.01 -> 0.095908474 | D43: =L29/$O$18 -> 406.03171 | E43: =M29/$O$18 -> 425.50845 | F43: =N29/$O$18 -> 444.9852 | G43: =O29/$O$18 -> 464.46194 | H43: =P29/$O$18 -> 483.93868 | J43: WACC | K43: =K44-0.01 -> 0.095908474 | L43: =D43 / $O$19-1 -> 0.0037866774 | M43: =E43 / $O$19-1 -> 0.051936846 | N43: =F43 / $O$19-1 -> 0.10008701 | O43: =G43 / $O$19-1 -> 0.14823718 | P43: =H43 / $O$19-1 -> 0.19638735
C44: =C45-0.01 -> 0.10590847 | D44: =L30/$O$18 -> 391.64746 | E44: =M30/$O$18 -> 410.38617 | F44: =N30/$O$18 -> 429.12488 | G44: =O30/$O$18 -> 447.86359 | H44: =P30/$O$18 -> 466.6023 | K44: =K45-0.01 -> 0.10590847 | L44: =D44 / $O$19-1 -> -0.031773886 | M44: =E44 / $O$19-1 -> 0.014551726 | N44: =F44 / $O$19-1 -> 0.060877339 | O44: =G44 / $O$19-1 -> 0.10720295 | P44: =H44 / $O$19-1 -> 0.15352856
C45: =O16 -> 0.11590847 | D45: =L31/$O$18 -> 377.91811 | E45: =M31/$O$18 -> 395.95302 | F45: =N31/$O$18 -> 413.98794 | G45: =O31/$O$18 -> 432.02285 | H45: =P31/$O$18 -> 450.05776 | K45: =O16 -> 0.11590847 | L45: =D45 / $O$19-1 -> -0.065715435 | M45: =E45 / $O$19-1 -> -0.021129738 | N45: =F45 / $O$19-1 -> 0.023455958 | O45: =G45 / $O$19-1 -> 0.068041655 | P45: =H45 / $O$19-1 -> 0.11262735
C46: =C45 + 0.01 -> 0.12590847 | D46: =L32/$O$18 -> 364.80814 | E46: =M32/$O$18 -> 382.17162 | F46: =N32/$O$18 -> 399.5351 | G46: =O32/$O$18 -> 416.89858 | H46: =P32/$O$18 -> 434.26206 | K46: =K45 + 0.01 -> 0.12590847 | L46: =D46 / $O$19-1 -> -0.098125736 | M46: =E46 / $O$19-1 -> -0.055199949 | N46: =F46 / $O$19-1 -> -0.012274162 | O46: =G46 / $O$19-1 -> 0.030651624 | P46: =H46 / $O$19-1 -> 0.073577411
C47: =C46 + 0.01 -> 0.13590847 | D47: =L33/$O$18 -> 352.28428 | E47: =M33/$O$18 -> 369.00694 | F47: =N33/$O$18 -> 385.72959 | G47: =O33/$O$18 -> 402.45224 | H47: =P33/$O$18 -> 419.1749 | K47: =K46 + 0.01 -> 0.13590847 | L47: =D47 / $O$19-1 -> -0.12908707 | M47: =E47 / $O$19-1 -> -0.087745524 | N47: =F47 / $O$19-1 -> -0.046403982 | O47: =G47 / $O$19-1 -> -0.0050624397 | P47: =H47 / $O$19-1 -> 0.036279102

Sheet Inputs
B8: Assumptions and Drivers | F8: 2
B10: All Figures in INR Crores unless stated | J10: 2026 | K10: =J10 + 1 -> 2027 | L10: =K10 + 1 -> 2028 | M10: =L10 + 1 -> 2029 | N10: Term
B13: Revenue Growth | J13: {=INDEX(J15:J17, $F$8)} -> 0.09 | K13: {=INDEX(K15:K17, $F$8)} -> 0.085 | L13: {=INDEX(L15:L17, $F$8)} -> 0.085 | M13: {=INDEX(M15:M17, $F$8)} -> 0.07 | N13: {=INDEX(N15:N17, $F$8)} -> 0.065
B15: Best Case | J15: 0.1 | K15: 0.1 | L15: 0.09 | M15: 0.085 | N15: 0.07
B16: Base Case | J16: 0.09 | K16: 0.085 | L16: 0.085 | M16: 0.07 | N16: 0.065
B17: Worst Case | J17: 0.085 | K17: 0.07 | L17: 0.07 | M17: 0.065 | N17: 0.06
B20: COGS | H20: (as % of revenue) | J20: {=INDEX(J22:J24, $F$8)} -> 0.425 | K20: {=INDEX(K22:K24, $F$8)} -> 0.43 | L20: {=INDEX(L22:L24, $F$8)} -> 0.44 | M20: {=INDEX(M22:M24, $F$8)} -> 0.445 | N20: {=INDEX(N22:N24, $F$8)} -> 0.45
B22: Best Case | J22: 0.4 | K22: 0.41 | L22: 0.425 | M22: 0.43 | N22: 0.44
B23: Base Case | J23: 0.425 | K23: 0.43 | L23: 0.44 | M23: 0.445 | N23: 0.45
B24: Worst Case | J24: 0.44 | K24: 0.445 | L24: 0.445 | M24: 0.45 | N24: 0.46
B27: SG&A | H27: (as % of revenue) | J27: {=INDEX(J29:J31, $F$8)} -> 0.205 | K27: {=INDEX(K29:K31, $F$8)} -> 0.21 | L27: {=INDEX(L29:L31, $F$8)} -> 0.21 | M27: {=INDEX(M29:M31, $F$8)} -> 0.215 | N27: {=INDEX(N29:N31, $F$8)} -> 0.22
B29: Best Case | J29: 0.2 | K29: 0.205 | L29: 0.205 | M29: 0.21 | N29: 0.21
B30: Base Case | J30: 0.205 | K30: 0.21 | L30: 0.21 | M30: 0.215 | N30: 0.22
B31: Worst Case | J31: 0.21 | K31: 0.215 | L31: 0.22 | M31: 0.22 | N31: 0.23
B34: Capital Expenditure | J34: {=INDEX(J36:J38, $F$8)} -> 2500 | K34: {=INDEX(K36:K38, $F$8)} -> 2600 | L34: {=INDEX(L36:L38, $F$8)} -> 2650 | M34: {=INDEX(M36:M38, $F$8)} -> 2700 | N34: {=INDEX(N36:N38, $F$8)} -> 2700
B36: Best Case | J36: 2300 | K36: 2400 | L36: 2500 | M36: 2550 | N36: 2600
B37: Base Case | J37: 2500 | K37: 2600 | L37: 2650 | M37: 2700 | N37: 2700
B38: Worst Case | J38: 2600 | K38: 2650 | L38: 2700 | M38: 2750 | N38: 2800
B41: Amounts Per Day
B43: Accounts Recievable | H43: (Days) | J43: 30 | K43: 30 | L43: 30 | M43: 30 | N43: 30
B44: Inventory | H44: (Days) | J44: 175 | K44: 175 | L44: 175 | M44: 175 | N44: 175
B45: Accounts Payable | H45: (Days) | J45: 75 | K45: 75 | L45: 75 | M45: 75 | N45: 75
B48: Weighted Average Cost of Capital (WACC)
B50: All Figures in INR Crores unless stated
K52: Debt/ | L52: Debt/ | M52: Levered | N52: Unlevered
B53: Name | E53: Region | H53: Debt | I53: Equity | J53: Tax Rate | K53: Equity | L53: Capital | M53: Beta | N53: Beta
B54: Britannia Industries Limited | E54: India | H54: 2196.3 | I54: 145243.58 | J54: 0.3 | K54: =H54/I54 -> 0.015121495 | L54: =H54 / (H54+I54) -> 0.014896241 | M54: 0.53 | N54: =M54 / (1 + (1 - J54) * K54) -> 0.52444869
B55: Nestle India | E55: India | H55: 476.85 | I55: 242909.75 | J55: 0.3 | K55: =H55/I55 -> 0.0019630748 | L55: =H55 / (H55+I55) -> 0.0019592287 | M55: 0.25 | N55: =M55 / (1 + (1 - J55) * K55) -> 0.24965693
B56: Hindustan Uniliver | E56: India | H56: 1775 | I56: 536223 | J56: 0.3 | K56: =H56/I56 -> 0.00331019 | L56: =H56 / (H56+I56) -> 0.0032992688 | M56: 0.32 | N56: =M56 / (1 + (1 - J56) * K56) -> 0.31926023
B57: Godrej Consumers | E57: India | H57: 4113.49 | I57: 122779.1 | J57: 0.3 | K57: =H57/I57 -> 0.033503178 | L57: =H57 / (H57+I57) -> 0.032417102 | M57: 0.23 | N57: =M57 / (1 + (1 - J57) * K57) -> 0.22472959
B58: Varun Beverages | E58: India | H58: 2138.25 | I58: 161794 | J58: 0.3 | K58: =H58/I58 -> 0.013215879 | L58: =H58 / (H58+I58) -> 0.013043498 | M58: 0.23 | N58: =M58 / (1 + (1 - J58) * K58) -> 0.22789175
I60: Average | J60: =AVERAGE(J54:J58) -> 0.3 | K60: =AVERAGE(K54:K58) -> 0.013422763 | L60: =AVERAGE(L54:L58) -> 0.013123068 | M60: =AVERAGE(M54:M58) -> 0.312 | N60: =AVERAGE(N54:N58) -> 0.30919744
I61: Median | J61: =MEDIAN(J54:J58) -> 0.3 | K61: =MEDIAN(K54:K58) -> 0.013215879 | L61: =MEDIAN(L54:L58) -> 0.013043498 | M61: =MEDIAN(M54:M58) -> 0.25 | N61: =MEDIAN(N54:N58) -> 0.24965693
B65: Risk Premium for Equity | I65: Cost of Equity
B67: Market Risk Premium | G67: 0.07 | I67: Risk Free Rate | N67: 0.065
B68: Average Unlevered Beta | G68: =N60 -> 0.30919744 | I68: Equity Risk Premium | N68: =G70 -> 0.0216514
B69: Levered Beta | G69: =G68 * (1 + (1 - N77) *G81) -> 0.30930571 | I69: Country Risk Premium | N69: 0.0293
B70: Equity Risk Premium | G70: =G67 * G69 -> 0.0216514 | I70: Cost of Equity | N70: =SUM(N67:N69) -> 0.1159514
B74: Capital Structure | I74: Cost of Debt
F76: Current | G76: Target | I76: Pre Tax Cost of Debt | N76: 0.043
B77: Total Debt | E77: 362.97 | F77: =E77 / E79 -> 0.0007119984 | G77: 0.0005 | I77: Tax Rate | N77: 0.3
B78: Market Capitilization | E78: 509427.5 | F78: =E78 / E79 -> 0.999288 | G78: =1-G77 -> 0.9995 | I78: After Tax Cost of Debt | N78: =N76* (1 - N77) -> 0.0301
B79: Total Capitilization | E79: =SUM(E77:E78) -> 509790.47 | F79: =SUM(F77:F78) -> 1 | G79: =SUM(G77:G78) -> 1
B81: Debt/Equity | F81: =F77 / F78 -> 0.0007125057 | G81: =G77/G78 -> 0.00050025013 | I81: Weighted Average Cost of Capital
M83: Weight | N83: Cost
I84: Debt Capital | M84: =G77 -> 0.0005 | N84: =N78 -> 0.0301
I85: Equity Capital | M85: =G78 -> 0.9995 | N85: =N70 -> 0.1159514
I88: Weighted Average Cost of Capital | N88: =SUMPRODUCT(M84:M85, N84:N85) -> 0.11590847
B91: Other Inputs
B94: Terminal Multiple | E94: 20 | I94: Valuation Date | L94: DD-MM-YY | N94: 46022
B95: Net Debt | E95: -3649.39 | I95: First Expected Cash Flow | L95: DD-MM-YY | N95: 46022
B96: PP&E at the end of 2025 | E96: 30209.28 | I96: First Fiscal Year End for Forecast | L96: DD-MM-YY | N96: 46112
B97: Shares Outstanding | E97: 1252.9 | I97: First Year of Forecast | N97: 2026
B98: Current Stock Price | D98: (INR/Share) | E98: 404.5 | I98: Incorrect Date Set for Valuation? | N98: =IF(N94>N95, 1, 0) -> 0
I99: Incorrect Date Set for First Cash Flow? | N99: =IF(N95>N96, 1, 0) -> 0
I100: Days in Period | N100: 365
G108: =Model!J155 -> 515036.09
F109: 1 | G109: 572330.78
F110: 2 | G110: 515036.09
F111: 3 | G111: 464836.83

Sheet Model
B8: Income Statement
B10: All Figures in INR Crores unless stated | H10: 2023 | I10: 2024 | J10: 2025 | K10: =J10 + 1 -> 2026 | L10: =K10 + 1 -> 2027 | M10: =L10 + 1 -> 2028 | N10: =M10 + 1 -> 2029 | O10: Term
B11: =_xlfn.CONCAT("Model Currently Running:"," ", INDEX(Inputs!$B$15:$B$17, Inputs!$F$8), " ", "Scenario") -> Model Currently Running: Base Case Scenario
B13: Revenue Growth | I13: =I21/H21-1 -> -0.040631661 | J13: =J21/I21-1 -> 0.10776329 | K13: =Inputs!J13 -> 0.09 | L13: =Inputs!K13 -> 0.085 | M13: =Inputs!L13 -> 0.085 | N13: =Inputs!M13 -> 0.07 | O13: =Inputs!N13 -> 0.065
B14: COGS | E14: (% of Revenue) | H14: =-H22/H21 -> 0.41939537 | I14: =-I22 / I21 -> 0.40577857 | J14: =-J22 / J21 -> 0.433686 | K14: =Inputs!J20 -> 0.425 | L14: =Inputs!K20 -> 0.43 | M14: =Inputs!L20 -> 0.44 | N14: =Inputs!M20 -> 0.445 | O14: =Inputs!N20 -> 0.45
B15: SG&A | E15: (% of Revenue) | H15: =-H25 / H21 -> 0.21466215 | I15: =-I25 / I21 -> 0.22046952 | J15: =-J25 / J21 -> 0.22018806 | K15: =Inputs!J27 -> 0.205 | L15: =Inputs!K27 -> 0.21 | M15: =Inputs!L27 -> 0.21 | N15: =Inputs!M27 -> 0.215 | O15: =Inputs!N27 -> 0.22
B16: Net Interest Income/(Expense) | H16: =H31 -> 1456.23 | I16: =I31 -> 1657.64 | J16: =J31 -> 1443.7 | K16: 1500 | L16: 1500 | M16: 1500 | N16: 1500 | O16: 1500
B17: Other Operating Income/(Expense) | H17: =H32 -> 153.13 | I17: =I32 -> 148.06 | J17: =J32 -> 151.21 | K17: 150 | L17: 150 | M17: 150 | N17: 150 | O17: 150
B18: Tax Rate | H18: =-H35 / H33 -> 0.25242629 | I18: =-I35 / I33 -> 0.24374548 | J18: =-J35 / J33 -> 0.26719634 | K18: 0.3 | L18: 0.3 | M18: 0.3 | N18: 0.3 | O18: 0.3
B21: Revenue | H21: 70245.22 | I21: 67391.04 | J21: 74653.32 | K21: =J21 * (1 + K13) -> 81372.119 | L21: =K21 * (1 + L13) -> 88288.749 | M21: =L21 * (1 + M13) -> 95793.293 | N21: =M21 * (1 + N13) -> 102498.82 | O21: =N21 * (1 + O13) -> 109161.25
B22: COGS | H22: -29460.52 | I22: -27345.84 | J22: -32376.1 | K22: =-(K21 * K14) -> -34583.15 | L22: =-(L21 * L14) -> -37964.162 | M22: =-(M21 * M14) -> -42149.049 | N22: =-(N21 * N14) -> -45611.976 | O22: =-(O21 * O14) -> -49122.561
B23: Gross Profit | H23: =SUM(H21:H22) -> 40784.7 | I23: =SUM(I21:I22) -> 40045.2 | J23: =SUM(J21:J22) -> 42277.22 | K23: =SUM(K21:K22) -> 46788.968 | L23: =SUM(L21:L22) -> 50324.587 | M23: =SUM(M21:M22) -> 53644.244 | N23: =SUM(N21:N22) -> 56886.847 | O23: =SUM(O21:O22) -> 60038.686
B25: SG&A | H25: -15078.99 | I25: -14857.67 | J25: -16437.77 | K25: =-(K21 * K15) -> -16681.284 | L25: =-(L21 * L15) -> -18540.637 | M25: =-(M21 * M15) -> -20116.591 | N25: =-(N21 * N15) -> -22037.247 | O25: =-(O21 * O15) -> -24015.474
B26: EBITDA | H26: =SUM(H23, H25) -> 25705.71 | I26: =SUM(I23, I25) -> 25187.53 | J26: =SUM(J23, J25) -> 25839.45 | K26: =SUM(K23, K25) -> 30107.684 | L26: =SUM(L23, L25) -> 31783.95 | M26: =SUM(M23, M25) -> 33527.652 | N26: =SUM(N23, N25) -> 34849.6 | O26: =SUM(O23, O25) -> 36023.211
B28: Depreciation & Amortisation | H28: -1809.01 | I28: -1518.05 | J28: -1646.32 | K28: =-K110 -> -1560.464 | L28: =-L110 -> -1662.464 | M28: =-M110 -> -1767.464 | N28: =-N110 -> -1874.464 | O28: =-Inputs!N34 -> -2700
B29: EBIT | H29: =SUM(H26, H28) -> 23896.7 | I29: =SUM(I26, I28) -> 23669.48 | J29: =SUM(J26, J28) -> 24193.13 | K29: =SUM(K26, K28) -> 28547.22 | L29: =SUM(L26, L28) -> 30121.486 | M29: =SUM(M26, M28) -> 31760.188 | N29: =SUM(N26, N28) -> 32975.136 | O29: =SUM(O26, O28) -> 33323.211
B31: Net Interest Income/(Expense) | H31: 1456.23 | I31: 1657.64 | J31: 1443.7 | K31: =K16 -> 1500 | L31: =L16 -> 1500 | M31: =M16 -> 1500 | N31: =N16 -> 1500 | O31: =O16 -> 1500
B32: Other Non Operating Income/(Expense) | H32: 153.13 | I32: 148.06 | J32: 151.21 | K32: =K17 -> 150 | L32: =L17 -> 150 | M32: =M17 -> 150 | N32: =N17 -> 150 | O32: =O17 -> 150
B33: EBT | H33: =SUM(H29, H31:H32) -> 25506.06 | I33: =SUM(I29, I31:I32) -> 25475.18 | J33: =SUM(J29, J31:J32) -> 25788.04 | K33: =SUM(K29, K31:K32) -> 30197.22 | L33: =SUM(L29, L31:L32) -> 31771.486 | M33: =SUM(M29, M31:M32) -> 33410.188 | N33: =SUM(N29, N31:N32) -> 34625.136 | O33: =SUM(O29, O31:O32) -> 34973.211
B35: Provision For Taxes | H35: -6438.4 | I35: -6209.46 | J35: -6890.47 | K35: =-K33 * K18 -> -9059.166 | L35: =-L33 * L18 -> -9531.4457 | M35: =-M33 * M18 -> -10023.057 | N35: =-N33 * N18 -> -10387.541 | O35: =-O33 * O18 -> -10491.963
B37: Net Income | H37: =SUM(H33, H35) -> 19067.66 | I37: =SUM(I33, I35) -> 19265.72 | J37: =SUM(J33, J35) -> 18897.57 | K37: =SUM(K33, K35) -> 21138.054 | L37: =SUM(L33, L35) -> 22240.04 | M37: =SUM(M33, M35) -> 23387.132 | N37: =SUM(N33, N35) -> 24237.595 | O37: =SUM(O33, O35) -> 24481.248
B40: Working Capital Schedule
B42: All Figures in INR Crores unless stated | H42: 2023 | I42: 2024 | J42: 2025 | K42: =J42 + 1 -> 2026 | L42: =K42 + 1 -> 2027 | M42: =L42 + 1 -> 2028 | N42: =M42 + 1 -> 2029 | O42: Term
B43: =_xlfn.CONCAT("Model Currently Running:"," ", INDEX(Inputs!$B$15:$B$17, Inputs!$F$8), " ", "Scenario") -> Model Currently Running: Base Case Scenario
B45: Days in Period | H45: 365 | I45: 365 | J45: 365 | K45: 365 | L45: 365 | M45: 365 | N45: 365 | O45: 365
B46: Revenue | H46: =H21 -> 70245.22 | I46: =I21 -> 67391.04 | J46: =J21 -> 74653.32 | K46: =K21 -> 81372.119 | L46: =L21 -> 88288.749 | M46: =M21 -> 95793.293 | N46: =N21 -> 102498.82 | O46: =O21 -> 109161.25
B47: COGS | H47: =-H22 -> 29460.52 | I47: =-I22 -> 27345.84 | J47: =-J22 -> 32376.1 | K47: =-K22 -> 34583.15 | L47: =-L22 -> 37964.162 | M47: =-M22 -> 42149.049 | N47: =-N22 -> 45611.976 | O47: =-O22 -> 49122.561
B50: Amounts Per Day
B51: Accounts Receivable | E51: (Days) | H51: =(H57 / H46)* H$45 -> 32.025798 | I51: =(I57 / I46)* I$45 -> 29.248674 | J51: =(J57 / J46)* J$45 -> 20.910856 | K51: =Inputs!J43 -> 30 | L51: =Inputs!K43 -> 30 | M51: =Inputs!L43 -> 30 | N51: =Inputs!M43 -> 30 | O51: =Inputs!N43 -> 30
B52: Inventory | E52: (Days) | H52: =(H58 / H47) * H45 -> 196.20126 | I52: =(I58 / I47) * I45 -> 190.90842 | J52: =(J58 / J47) * J45 -> 134.3169 | K52: =Inputs!J44 -> 175 | L52: =Inputs!K44 -> 175 | M52: =Inputs!L44 -> 175 | N52: =Inputs!M44 -> 175 | O52: =Inputs!N44 -> 175
B53: Accounts Payable | E53: (Days) | H53: =(H59/H47) * H45 -> 78.030692 | I53: =(I59/I47) * I45 -> 79.977326 | J53: =(J59/J47) * J45 -> 65.523814 | K53: =Inputs!J45 -> 75 | L53: =Inputs!K45 -> 75 | M53: =Inputs!L45 -> 75 | N53: =Inputs!M45 -> 75 | O53: =Inputs!N45 -> 75
B56: Total Amounts
B57: Accounts Receivable | H57: 6163.45 | I57: 5400.27 | J57: 4276.89 | K57: =(K51 / K45) * K46 -> 6688.1194 | L57: =(L51 / L45) * L46 -> 7256.6095 | M57: =(M51 / M45) * M46 -> 7873.4213 | N57: =(N51 / N45) * N46 -> 8424.5608 | O57: =(O51 / O45) * O46 -> 8972.1572
B58: Inventory | H58: 15836.14 | I58: 14302.88 | J58: 11914.13 | K58: =(K52 / K45) * K47 -> 16580.963 | L58: =(L52 / L45) * L47 -> 18201.995 | M58: =(M52 / M45) * M47 -> 20208.448 | N58: =(N52 / N45) * N47 -> 21868.756 | O58: =(O52 / O45) * O47 -> 23551.913
B59: Accounts Payable | H59: 6298.15 | I59: 5991.91 | J59: 5812.07 | K59: =(K53/K45) * K47 -> 7106.1268 | L59: =(L53/L45) * L47 -> 7800.8552 | M59: =(M53/M45) * M47 -> 8660.7634 | N59: =(N53/N45) * N47 -> 9372.3239 | O59: =(O53/O45) * O47 -> 10093.677
B62: Net Working Capital
B63: Current Assets | H63: =H57+ H58 -> 21999.59 | I63: =I57+ I58 -> 19703.15 | J63: =J57+ J58 -> 16191.02 | K63: =K57+ K58 -> 23269.082 | L63: =L57+ L58 -> 25458.605 | M63: =M57+ M58 -> 28081.869 | N63: =N57+ N58 -> 30293.317 | O63: =O57+ O58 -> 32524.07
B64: Current Liabilities | H64: =H59 -> 6298.15 | I64: =I59 -> 5991.91 | J64: =J59 -> 5812.07 | K64: =K59 -> 7106.1268 | L64: =L59 -> 7800.8552 | M64: =M59 -> 8660.7634 | N64: =N59 -> 9372.3239 | O64: =O59 -> 10093.677
B65: Net Working Capital | H65: =H63-H64 -> 15701.44 | I65: =I63-I64 -> 13711.24 | J65: =J63-J64 -> 10378.95 | K65: =K63-K64 -> 16162.955 | L65: =L63-L64 -> 17657.75 | M65: =M63-M64 -> 19421.106 | N65: =N63-N64 -> 20920.993 | O65: =O63-O64 -> 22430.393
B68: Cash From Working Capital | I68: =H65-I65 -> 1990.2 | J68: =I65-J65 -> 3332.29 | K68: =J65-K65 -> -5784.0051 | L68: =K65-L65 -> -1494.7947 | M68: =L65-M65 -> -1763.3561 | N68: =M65-N65 -> -1499.8868 | O68: =N65-O65 -> -1509.4005
B71: Depreciation Schedule
B73: All Figures in INR Crores unless stated | H73: 2023 | I73: 2024 | J73: 2025 | K73: =J73 + 1 -> 2026 | L73: =K73 + 1 -> 2027 | M73: =L73 + 1 -> 2028 | N73: =M73 + 1 -> 2029
B74: =_xlfn.CONCAT("Model Currently Running:"," ", INDEX(Inputs!$B$15:$B$17, Inputs!$F$8), " ", "Scenario") -> Model Currently Running: Base Case Scenario
B76: Capital Expenditure | H76: 1833.91 | I76: 2617.9 | J76: 2610.63 | K76: =Inputs!J34 -> 2500 | L76: =Inputs!K34 -> 2600 | M76: =Inputs!L34 -> 2650 | N76: =Inputs!M34 -> 2700
B79: Existing Asset Depreciation | E79: Years | L79: Percent of Full Year
B80: Useful Life : Existing Assets | E80: 20 | K80: Yr1 | L80: Yr2 | M80: Yr3 | N80: Yr4
B81: PP&E at end of 2025 | E81: =Inputs!E96 -> 30209.28 | K81: =MIN($E80-SUM($J81:J81), 1) -> 1 | L81: =MIN($E80-SUM($J81:K81), 1) -> 1 | M81: =MIN($E80-SUM($J81:L81), 1) -> 1 | N81: =MIN($E80-SUM($J81:M81), 1) -> 1
B86: New Asset Depreciation | E86: Years | L86: Percent of Full Year
B87: Useful Life : New Assets | E87: 25 | K87: Yr1 | L87: Yr2 | M87: Yr3 | N87: Yr4
B88: First Year Accounting Depreciation | E88: 0.5 | K88: =IF(J88="",E88,MIN($E87-SUM($J88:J88),1)) -> 0.5 | L88: =IF(K88="",F88,MIN($E87-SUM($J88:K88),1)) -> 1 | M88: =IF(L88="",G88,MIN($E87-SUM($J88:L88),1)) -> 1 | N88: =IF(M88="",H88,MIN($E87-SUM($J88:M88),1)) -> 1
L91: Percent of Full Year
H92: Year | I92: Life | K92: 2026 | L92: =K92 + 1 -> 2027 | M92: =L92 + 1 -> 2028 | N92: =M92 + 1 -> 2029
H93: 2026 | I93: =$E$87 -> 25 | K93: =K88 -> 0.5 | L93: =L88 -> 1 | M93: =M88 -> 1 | N93: =N88 -> 1
H94: =H93 + 1 -> 2027 | I94: =$E$87 -> 25 | K94: =J93 -> 0 | L94: =K93 -> 0.5 | M94: =L93 -> 1 | N94: =M93 -> 1
H95: =H94 + 1 -> 2028 | I95: =$E$87 -> 25 | K95: =J94 -> 0 | L95: =K94 -> 0 | M95: =L94 -> 0.5 | N95: =M94 -> 1
H96: =H95 + 1 -> 2029 | I96: =$E$87 -> 25 | K96: =J95 -> 0 | L96: =K95 -> 0 | M96: =L95 -> 0 | N96: =M95 -> 0.5
H99: Year | I99: Capex | J99: Per Yr | K99: 2026 | L99: =K99 + 1 -> 2027 | M99: =L99 + 1 -> 2028 | N99: =M99 + 1 -> 2029
H100: 2026 | I100: =SUMIF($K$73:$N$73, H100, $K$76:$N$76) -> 2500 | J100: =I100 / I93 -> 100 | K100: =$J100 * K93 -> 50 | L100: =$J100 * L93 -> 100 | M100: =$J100 * M93 -> 100 | N100: =$J100 * N93 -> 100
H101: =H100 + 1 -> 2027 | I101: =SUMIF($K$73:$N$73, H101, $K$76:$N$76) -> 2600 | J101: =I101 / I94 -> 104 | K101: =$J101 * K94 -> 0 | L101: =$J101 * L94 -> 52 | M101: =$J101 * M94 -> 104 | N101: =$J101 * N94 -> 104
H102: =H101 + 1 -> 2028 | I102: =SUMIF($K$73:$N$73, H102, $K$76:$N$76) -> 2650 | J102: =I102 / I95 -> 106 | K102: =$J102 * K95 -> 0 | L102: =$J102 * L95 -> 0 | M102: =$J102 * M95 -> 53 | N102: =$J102 * N95 -> 106
H103: =H102 + 1 -> 2029 | I103: =SUMIF($K$73:$N$73, H103, $K$76:$N$76) -> 2700 | J103: =I103 / I96 -> 108 | K103: =$J103 * K96 -> 0 | L103: =$J103 * L96 -> 0 | M103: =$J103 * M96 -> 0 | N103: =$J103 * N96 -> 54
B107: Total Asset Depriciation
B108: Existing Assets | K108: =($E$81/$E$80)*K81 -> 1510.464 | L108: =($E$81/$E$80)*L81 -> 1510.464 | M108: =($E$81/$E$80)*M81 -> 1510.464 | N108: =($E$81/$E$80)*N81 -> 1510.464
B109: New Assets | K109: =SUM(K100:K103) -> 50 | L109: =SUM(L100:L103) -> 152 | M109: =SUM(M100:M103) -> 257 | N109: =SUM(N100:N103) -> 364
B110: Total Depreciation | K110: =SUM(K108:K109) -> 1560.464 | L110: =SUM(L108:L109) -> 1662.464 | M110: =SUM(M108:M109) -> 1767.464 | N110: =SUM(N108:N109) -> 1874.464
B113: Unlevered Free Cash Flow Schedule
B115: All Figures in INR Crores unless stated | I115: 2024 | J115: 2025 | K115: =J115 + 1 -> 2026 | L115: =K115 + 1 -> 2027 | M115: =L115 + 1 -> 2028 | N115: =M115 + 1 -> 2029 | O115: Term
B116: =_xlfn.CONCAT("Model Currently Running:"," ", INDEX(Inputs!$B$15:$B$17, Inputs!$F$8), " ", "Scenario") -> Model Currently Running: Base Case Scenario
B119: Unlevered Free Cash Flow
B120: EBIT | I120: =I29 -> 23669.48 | J120: =J29 -> 24193.13 | K120: =K29 -> 28547.22 | L120: =L29 -> 30121.486 | M120: =M29 -> 31760.188 | N120: =N29 -> 32975.136 | O120: =O29 -> 33323.211
B121: Current Taxes | I121: =I35 -> -6209.46 | J121: =J35 -> -6890.47 | K121: =K35 -> -9059.166 | L121: =L35 -> -9531.4457 | M121: =M35 -> -10023.057 | N121: =N35 -> -10387.541 | O121: =O35 -> -10491.963
B122: NOPAT | I122: =SUM(I120:I121) -> 17460.02 | J122: =SUM(J120:J121) -> 17302.66 | K122: =SUM(K120:K121) -> 19488.054 | L122: =SUM(L120:L121) -> 20590.04 | M122: =SUM(M120:M121) -> 21737.132 | N122: =SUM(N120:N121) -> 22587.595 | O122: =SUM(O120:O121) -> 22831.248
B123: Depreciation & Amortisation | I123: =-I28 -> 1518.05 | J123: =-J28 -> 1646.32 | K123: =-K28 -> 1560.464 | L123: =-L28 -> 1662.464 | M123: =-M28 -> 1767.464 | N123: =-N28 -> 1874.464 | O123: =-O28 -> 2700
B124: Capital Expenditure | I124: =-I76 -> -2617.9 | J124: =-J76 -> -2610.63 | K124: =-K76 -> -2500 | L124: =-L76 -> -2600 | M124: =-M76 -> -2650 | N124: =-N76 -> -2700 | O124: =-Inputs!N34 -> -2700
B125: Cash From Working Capital | I125: =I68 -> 1990.2 | J125: =J68 -> 3332.29 | K125: =K68 -> -5784.0051 | L125: =L68 -> -1494.7947 | M125: =M68 -> -1763.3561 | N125: =N68 -> -1499.8868 | O125: =O68 -> -1509.4005
B126: Unlevered Free Cash Flow | I126: =SUM(I122:I125) -> 18350.37 | J126: =SUM(J122:J125) -> 19670.64 | K126: =SUM(K122:K125) -> 12764.513 | L126: =SUM(L122:L125) -> 18157.709 | M126: =SUM(M122:M125) -> 19091.24 | N126: =SUM(N122:N125) -> 20262.172 | O126: =SUM(O122:O125) -> 21321.847
B129: Discounted Cash Flow Schedule
B131: All Figures in INR Crores unless stated | J131: Valuation | L131: Discrete Forecast | O131: Term
B132: =_xlfn.CONCAT("Model Currently Running:"," ", INDEX(Inputs!$B$15:$B$17, Inputs!$F$8), " ", "Scenario") -> Model Currently Running: Base Case Scenario | J132: DD-MM-YY | K132: DD-MM-YY | L132: DD-MM-YY | M132: DD-MM-YY | N132: DD-MM-YY | O132: DD-MM-YY
H133: Fiscal Year End | J133: =Inputs!N94 -> 46022 | K133: =Inputs!N96 -> 46112 | L133: =EDATE(K133, 12) -> 46477 | M133: =EDATE(L133, 12) -> 46843 | N133: =EDATE(M133, 12) -> 47208 | O133: =EDATE(N133, 12) -> 47573
H134: Cash Flow Timing | J134: =J133 -> 46022 | K134: =Inputs!N95 -> 46022 | L134: =EDATE(K134, 12) -> 46387 | M134: =EDATE(L134, 12) -> 46752 | N134: =EDATE(M134, 12) -> 47118 | O134: =EDATE(N134, 12) -> 47483
B136: Unlevered Free Cash Flow | K136: =K126 -> 12764.513 | L136: =L126 -> 18157.709 | M136: =M126 -> 19091.24 | N136: =N126 -> 20262.172 | O136: =O126 -> 21321.847
B137: EBITDA | O137: =O26 -> 36023.211
B140: Unadjusted Cash Flow
B141: Discrete Forecast | G141: Terminal | J141: 0 | K141: =K136 -> 12764.513 | L141: =L136 -> 18157.709 | M141: =M136 -> 19091.24 | N141: =N136 -> 20262.172 | O141: =O136 -> 21321.847
B142: Terminal Value | G142: Adjustment | J142: 0 | K142: 0 | L142: 0 | M142: 0 | N142: 0 | O142: =( O137 *D153)/(1 + D154) ^ G143 -> 700979.44
B143: Total Cash Flow | G143: =YEARFRAC(O134, O133) -> 0.25 | J143: =SUM(J141:J142) -> 0 | K143: =SUM(K141:K142) -> 12764.513 | L143: =SUM(L141:L142) -> 18157.709 | M143: =SUM(M141:M142) -> 19091.24 | N143: =SUM(N141:N142) -> 20262.172 | O143: =D153*O137 -> 720464.23
B145: Adjusted Cash Flow
B146: Partial Period Adjustment | J146: 0 | K146: =YEARFRAC(K133, J133) -> 0.25 | L146: =YEARFRAC(L133, K133) -> 1 | M146: =YEARFRAC(M133, L133) -> 1 | N146: =YEARFRAC(N133, M133) -> 1 | O146: =YEARFRAC(O133, N133) -> 1
B147: Discrete Forecast | J147: 0 | K147: =K141 * K$146 -> 3191.1282 | L147: =L141 * L$146 -> 18157.709 | M147: =M141 * M$146 -> 19091.24 | N147: =N141 * N$146 -> 20262.172 | O147: =O141 * O$146 -> 21321.847
B148: Terminal Value | J148: 0 | K148: =K142 * K$146 -> 0 | L148: =L142 * L$146 -> 0 | M148: =M142 * M$146 -> 0 | N148: =N142 * N$146 -> 0 | O148: =O142 * O$146 -> 700979.44
B149: Total Cash Flow | J149: 0 | K149: =SUM(K147:K148) -> 3191.1282 | L149: =SUM(L147:L148) -> 18157.709 | M149: =SUM(M147:M148) -> 19091.24 | N149: =SUM(N147:N148) -> 20262.172 | O149: =SUM(O147:O148) -> 722301.28
B152: Assumptions | G152: Enterprise Value | L152: Equity Value per Share
B153: Terminal Multiple | D153: =Inputs!E94 -> 20 | G153: PV of Discreet | J153: =XNPV(D154,J147:O147,J134:O134) -> 63117.213 | L153: Equity Value | O153: =J162 -> 518685.48
B154: Discount Rate | D154: =Inputs!N88 -> 0.11590847 | G154: PV of Terminal | J154: =XNPV(D154, J148:O148, J134:O134) -> 451918.88 | L154: Shares Outstanding | O154: =Inputs!E97 -> 1252.9
G155: Enterprise Value | J155: =SUM(J153:J154) -> 515036.09 | L155: Equity Value per Share | N155: (INR/Share) | O155: =O153/O154 -> 413.98794
G159: Equity Value
G160: Enterprise Value | J160: =J155 -> 515036.09
G161: Net Debt (1) | J161: =Inputs!E95 -> -3649.39
G162: Equity Value | J162: =J160-J161 -> 518685.48
...

Sheet HIS
B1: 45016 | C1: 45382 | D1: 45747
A2: Operating Revenue | B2: 70245.22 | C2: 67391.04 | D2: 74653.32 | F2: 10000000
A3: Total Revenue | B3: 70245.22 | C3: 67391.04 | D3: 74653.32
A4: Cost Of Revenue | B4: 29460.52 | C4: 27345.84 | D4: 32376.1
A5: Gross Profit | B5: 40784.7 | C5: 40045.2 | D5: 42277.22
A6: Rent And Landing Fees | B6: 266.46 | C6: 274.3 | D6: 307.2
A7: General And Administrative Expense | B7: 874.04 | C7: 858.91 | D7: 912.36
A8: Selling And Marketing Expense | B8: 1271.01 | C8: 3038.93 | D8: 3316.94
A9: Selling General And Administration | B9: 2145.05 | C9: 3897.84 | D9: 4229.3
A10: Research And Development | B10: 204.72 | C10: 242.15 | D10: 0
A11: Depreciation Income Statement | B11: 1809.01 | C11: 1518.05 | D11: 1646.32
A12: Depreciation And Amortization In Income Statement | B12: 1809.01 | C12: 1518.05 | D12: 1646.32
A13: Other Operating Expenses | B13: 7418.17 | C13: 5677.9 | D13: 6401.51
A14: Operating Expense | B14: 16888 | C14: 16375.72 | D14: 18084.09
... A54: Tax Effect Of Unusual Items | B54: 80.246713 | C54: 211.83207 | D54: 262.15166

Sheet HBS
B1: 44651 | C1: 45016 | D1: 45382 | E1: 45747
A2: Cash Financial | B2: 268.25 | C2: 458.27 | D2: 487.23 | E2: 417.4 | G2: 10000000
A3: Cash Equivalents | B3: 3.12 | C3: 5.08 | D3: 138.66 | E3: 202.6
A4: Cash And Cash Equivalents | B4: 271.37 | C4: 463.35 | D4: 625.89 | E4: 620
A5: Other Short Term Investments | B5: 16422.84 | C5: 21410.27 | D5: 19267.27 | E5: 19415.02
A6: Cash Cash Equivalents And Short Term Investments | B6: 16694.21 | C6: 21873.62 | D6: 19893.16 | E6: 20035.02
A7: Gross Accounts Receivable | B7: 2658.77 | C7: 3153.72 | D7: 4213.95 | E7: 4895.8
A8: Allowance For Doubtful Accounts Receivable | B8: -196.87 | C8: -197.55 | D8: -188.13 | E8: -176.13
A9: Accounts Receivable | B9: 2461.9 | C9: 2956.17 | D9: 4025.82 | E9: 4719.67
A10: Other Receivables | B10: 1214.86 | C10: 1320.72 | D10: 1374.45 | E10: 1443.78
A11: Raw Materials | B11: 7075.88 | C11: 7665.98 | D11: 9376.73 | E11: 11189.95
A12: Work In Process | B12: 732.41 | C12: 961.08 | D12: 1334.72 | E12: 414.6
A13: Finished Goods | B13: 2975.97 | C13: 3029.01 | D13: 3345.7 | E13: 3928.69
A14: Other Inventories | B14: 189.33 | C14: 258.06 | D14: 245.73 | E14: 302.9
... A82: Ordinary Shares Number | B82: 1232.3256 | C82: 1242.8018 | D82: 1248.4721 | E82: 1251.412
